ckbpy/__init__.py
ckbpy/constants.py
ckbpy/effect.py
ckbpy/params.py
ckbpy/types.py
ckbpy-0.0.1.dist-info/DESCRIPTION.rst
ckbpy-0.0.1.dist-info/METADATA
ckbpy-0.0.1.dist-info/RECORD
ckbpy-0.0.1.dist-info/WHEEL
ckbpy-0.0.1.dist-info/metadata.json
ckbpy-0.0.1.dist-info/top_level.txt
ckbpy-0.0.1.dist-info/zip-safe
