Metadata-Version: 2.0
Name: ckbpy
Version: 0.0.1
Summary: Write ckb effects using Python!
Home-page: http://github.com/cmd-johnson/ckbpy
Author: Jonas Auer
Author-email: jonas.auer.94@gmail.com
License: GPL-2.0
Platform: UNKNOWN
